desktop_control.py
feedback_memory.py
gui.py
llm_interface.py
logging_utils.py
main.py
n8n_interface.py
screen_capture.py
server.py
voice_input.py
ai_assistant_zimgar-0.1.1.dist-info/licenses/LICENSE
ai_assistant_zimgar-0.1.1.dist-info/METADATA
ai_assistant_zimgar-0.1.1.dist-info/WHEEL
ai_assistant_zimgar-0.1.1.dist-info/entry_points.txt
ai_assistant_zimgar-0.1.1.dist-info/top_level.txt
ai_assistant_zimgar-0.1.1.dist-info/RECORD
