Metadata-Version: 2.4
Name: ai-assistant-zimgar
Version: 0.1.1
Summary: Automates desktop tasks with help from a language model.
Author: AI Assistant
Maintainer-email: AI Assistant Maintainer <maintainer@example.com>
License: MIT License
Project-URL: Homepage, https://github.com/example/ai-assistant
Project-URL: Source, https://github.com/example/ai-assistant
Project-URL: Tracker, https://github.com/example/ai-assistant/issues
Classifier: Development Status :: 3 - Alpha
Classifier: Programming Language :: Python :: 3
Classifier: License :: OSI Approved :: MIT License
Classifier: Operating System :: OS Independent
Requires-Python: >=3.9
License-File: LICENSE
Requires-Dist: pyautogui
Requires-Dist: pynput
Requires-Dist: requests
Requires-Dist: openai
Requires-Dist: numpy
Requires-Dist: opencv-python
Requires-Dist: mss
Requires-Dist: SpeechRecognition
Requires-Dist: pyaudio
Requires-Dist: fastapi
Requires-Dist: uvicorn
Requires-Dist: httpx<0.24
Dynamic: license-file
